shalooprust-0.2.0.dist-info/METADATA
shalooprust-0.2.0.dist-info/WHEEL
shalooprust/__init__.py
shalooprust/__pycache__/__init__.cpython-37.pyc
shalooprust/__pycache__/__init__.cpython-38.pyc
shalooprust/__pycache__/pywrapper.cpython-38.pyc
shalooprust/__pycache__/pywrapper.cpython-37.pyc
shalooprust/__pycache__/ffi.cpython-37.pyc
shalooprust/__pycache__/ffi.cpython-38.pyc
shalooprust/pywrapper.py
shalooprust/shalooprust/__init__.py
shalooprust/shalooprust/ffi.py
shalooprust/shalooprust/native.so
shalooprust-0.2.0.dist-info/RECORD
