Metadata-Version: 2.1
Name: shalooprust
Version: 0.2.0
Requires-Dist: numpy>=1
Requires-Dist: cffi>=1
Requires-Dist: pycparser>=2
Home-Page: https://github.com/LaRiffle/shaloop
Author: Pierre Tholoniat <pierre@tholoniat.com>
Author-Email: Pierre Tholoniat <pierre@tholoniat.com>
Maintainer: Pierre Tholoniat
Maintainer-Email: pierre@tholoniat.com
License: Apache-2.0
Requires-Python: >=3.6
